timecraftx/__init__.py
timecraftx/constants.py
timecraftx/core.py
timecraftx/day.py
timecraftx/utils.py
timecraftx-1.0.2.dist-info/licenses/LICENSE
timecraftx-1.0.2.dist-info/WHEEL
timecraftx-1.0.2.dist-info/METADATA
timecraftx-1.0.2.dist-info/RECORD
