Metadata-Version: 2.4
Name: timecraftx
Version: 1.0.2
Summary: Lightweight utilities for working with dates and time in Python.
Keywords: date,datetime,week,utilities,time
Author-email: Jacobo Tapia <jatapiaro@gmail.com>
Requires-Python: >=3.7
License-File: LICENSE
Project-URL: Homepage, https://github.com/Jatapiaro/timecraft
Project-URL: Source, https://github.com/Jatapiaro/timecraft
